hikariwave/__init__.py
hikariwave/client.py
hikariwave/config.py
hikariwave/connection.py
hikariwave/py.typed
hikariwave/audio/__init__.py
hikariwave/audio/ffmpeg.py
hikariwave/audio/player.py
hikariwave/audio/store.py
hikariwave/audio/source/__init__.py
hikariwave/audio/source/base.py
hikariwave/audio/source/buffer.py
hikariwave/audio/source/file.py
hikariwave/audio/source/url.py
hikariwave/audio/source/youtube.py
hikariwave/event/__init__.py
hikariwave/event/factory.py
hikariwave/event/types.py
hikariwave/event/events/__init__.py
hikariwave/event/events/audio.py
hikariwave/event/events/base.py
hikariwave/event/events/bot.py
hikariwave/event/events/member.py
hikariwave/event/events/voice.py
hikariwave/internal/__init__.py
hikariwave/internal/constants.py
hikariwave/internal/dave.py
hikariwave/internal/encrypt.py
hikariwave/internal/error.py
hikariwave/internal/result.py
hikariwave/internal/signal.py
hikariwave/internal/websocket.py
hikariwave/networking/__init__.py
hikariwave/networking/gateway.py
hikariwave/networking/server.py
hikariwave/utils/__init__.py
hikariwave/utils/youtube.py
hikari_wave-0.6.0a1.dist-info/METADATA
hikari_wave-0.6.0a1.dist-info/WHEEL
hikari_wave-0.6.0a1.dist-info/licenses/LICENSE
hikari_wave-0.6.0a1.dist-info/RECORD
