Metadata-Version: 2.4
Name: hikari-wave
Version: 0.6.0a1
Summary: A lightweight, native voice implementation for hikari-based Discord bots
Project-URL: Homepage, https://github.com/WilDev-Studios/hikari-wave
Project-URL: Repository, https://github.com/WilDev-Studios/hikari-wave
Project-URL: Documentation, https://hikari-wave.wildevstudios.net/
Project-URL: Issues, https://github.com/WilDev-Studios/hikari-wave/issues
Author-email: WilDev Studios <wildevstudios@gmail.com>
Maintainer-email: WilDev Studios <wildevstudios@gmail.com>
License-Expression: MIT
License-File: LICENSE
Keywords: async,audio,bot,dave,discord,hikari,music,voice,youtube
Classifier: Development Status :: 4 - Beta
Classifier: Framework :: AsyncIO
Classifier: Intended Audience :: Developers
Classifier: Natural Language :: English
Classifier: Operating System :: OS Independent
Classifier: Programming Language :: Python :: 3
Classifier: Programming Language :: Python :: 3.10
Classifier: Programming Language :: Python :: 3.11
Classifier: Programming Language :: Python :: 3.12
Classifier: Programming Language :: Python :: 3.13
Classifier: Programming Language :: Python :: 3.14
Classifier: Programming Language :: Python :: Implementation :: CPython
Classifier: Topic :: Communications
Classifier: Typing :: Typed
Requires-Python: <3.15,>=3.10
Requires-Dist: aiofiles<26,>=25.1.0
Requires-Dist: cryptography<47,>=46.0.3
Requires-Dist: davey<1,>=0.1.3
Requires-Dist: hikari<3,>=2.5
Requires-Dist: pynacl<2,>=1.6
Requires-Dist: websockets<16,>=15.0
Requires-Dist: yt-dlp==2025.12.8
Provides-Extra: speedups
Requires-Dist: orjson<4,>=3.11.5; extra == 'speedups'
